energytool/__init__.py
energytool/building.py
energytool/modifier.py
energytool/outputs.py
energytool/system.py
energytool/tools.py
energytool/variant.py
energytool/base/__init__.py
energytool/base/idf_utils.py
energytool/base/idfobject_utils.py
energytool/base/parse_results.py
energytool/base/units.py
energytool/resources/resources.json
energytool-0.2.2.dist-info/licenses/LICENSE.md
energytool-0.2.2.dist-info/WHEEL
energytool-0.2.2.dist-info/METADATA
energytool-0.2.2.dist-info/RECORD
