Metadata-Version: 2.4
Name: energytool
Version: 0.2.2
Summary: Edit IDF files run EnergyPlus and process results
Author-email: Baptiste Durand-Estebe <b.durandestebe@gmail.com>
Maintainer-email: Baptiste Durand-Estebe <b.durandestebe@gmail.com>
Requires-Python: >=3.10
Classifier: Development Status :: 4 - Beta
Classifier: Intended Audience :: Developers
Classifier: License :: OSI Approved :: BSD License
Classifier: Programming Language :: Python :: 3
Classifier: Programming Language :: Python :: 3.10
Classifier: Programming Language :: Python :: 3.11
Classifier: Programming Language :: Python :: 3.12
Classifier: Programming Language :: Python :: 3.13
License-File: LICENSE.md
Requires-Dist: corrai>=1.0.0
Requires-Dist: ipython >= 8.13.0
Requires-Dist: numpy>=1.22.4, <2.0
Requires-Dist: pandas>=2.0.0, <3.0
Requires-Dist: eppy>=0.5.63
Requires-Dist: pytest>=7.0.0 ; extra == "dev"
Requires-Dist: pre-commit>=3.3.3 ; extra == "dev"
Requires-Dist: bump2version>=1.0.1 ; extra == "dev"
Requires-Dist: jupyter_contrib_nbextensions>=0.7.0 ; extra == "dev"
Project-URL: Source, https://github.com/BuildingEnergySimulationTools/energytool
Provides-Extra: dev
